README.txt
setup.py
bpmicro/__init__.py
bpmicro/bp1410.py
bpmicro/bp1410_fw.py
bpmicro/bp1410_fw_fx2.py
bpmicro/bp1410_fw_sn.py
bpmicro/cmd.py
bpmicro/device.py
bpmicro/devices.py
bpmicro/startup.py
bpmicro/usb.py
bpmicro/util.py
bpmicro.egg-info/PKG-INFO
bpmicro.egg-info/SOURCES.txt
bpmicro.egg-info/dependency_links.txt
bpmicro.egg-info/requires.txt
bpmicro.egg-info/top_level.txt