Metadata-Version: 1.1
Name: bpmicro
Version: 1.0.0
Summary: BP Microsystems open source driver.
Home-page: https://github.com/JohnDMcMaster/bpmicro
Author: John McMaster
Author-email: JohnDMcMaster@gmail.com
License: BSD
Keywords: EPROM programmer BPMicrosystems
Platform: UNKNOWN
Classifier: License :: OSI Approved :: BSD License
